projectPCA/__init__.py
projectPCA/eigenstrat_funcs.py
projectPCA/get_proj_files.py
projectPCA/loadEigenstrat.py
projectPCA/plot_pca.py
projectPCA/proj_pca.py
projectPCA/run.py
projectPCA/data/joscha_v1/joscha.ho_proj.maf05.tsv
projectPCA/data/joscha_v1/joscha.popres_proj.maf05.tsv
projectPCA/data/joscha_v1/joscha.weights_p.tsv
projectPCA/data/we_v1/20250422.ho_projections.tsv
projectPCA/data/we_v1/20250422.ho_ptn_weights_p.tsv
projectpca-0.2a1.dist-info/licenses/LICENSE
projectpca-0.2a1.dist-info/METADATA
projectpca-0.2a1.dist-info/WHEEL
projectpca-0.2a1.dist-info/top_level.txt
projectpca-0.2a1.dist-info/RECORD
