Metadata-Version: 2.4
Name: projectPCA
Version: 0.2a1
Summary: Project (ancient) human genomes onto pre-computed standard PCA
Author-email: Harald Ringbauer <harald_ringbauer@eva.mpg.de>
Maintainer-email: Harald Ringbauer <harald_ringbauer@eva.mpg.de>
License-Expression: GPL-3.0-or-later
Keywords: PCA,ancient DNA,eigenstrat,low coverage
Classifier: Programming Language :: Python :: 3
Classifier: Operating System :: OS Independent
Classifier: Topic :: Scientific/Engineering :: Bio-Informatics
Requires-Python: >=3.6
License-File: LICENSE
Requires-Dist: numpy
Requires-Dist: pandas
Requires-Dist: matplotlib
Dynamic: license-file
